pandoc_figure/__init__.py
pandoc_figure/_main.py
pandoc_figure-0.2.0.0.dist-info/METADATA
pandoc_figure-0.2.0.0.dist-info/WHEEL
pandoc_figure-0.2.0.0.dist-info/entry_points.txt
pandoc_figure-0.2.0.0.dist-info/licenses/LICENSE
pandoc_figure-0.2.0.0.dist-info/RECORD
