Metadata-Version: 2.4
Name: pandoc-figure
Version: 0.2.0.0
Summary: A pandoc filter for adding complex figures
Project-URL: Homepage, https://github.com/chdemko/pandoc-figure
Project-URL: Documentation, https://pandoc-figure.readthedocs.io/
Project-URL: Repository, https://github.com/chdemko/pandoc-figure
Project-URL: Issues, https://github.com/chdemko/pandoc-figure/issues
Author-email: Christophe Demko <chdemko@gmail.com>
Maintainer-email: Christophe Demko <chdemko@gmail.com>
License: BSD-3-Clause
License-File: LICENSE
Keywords: figure,filters,pandoc
Classifier: Development Status :: 4 - Beta
Classifier: Environment :: Console
Classifier: Intended Audience :: Developers
Classifier: Intended Audience :: End Users/Desktop
Classifier: Natural Language :: English
Classifier: Operating System :: OS Independent
Classifier: Programming Language :: Python :: 3.10
Classifier: Programming Language :: Python :: 3.11
Classifier: Programming Language :: Python :: 3.12
Classifier: Programming Language :: Python :: 3.13
Classifier: Topic :: Software Development :: Build Tools
Classifier: Topic :: Software Development :: Documentation
Classifier: Topic :: Text Processing :: Filters
Requires-Python: <3.14,>=3.10
Requires-Dist: panflute~=2.3
